treep/__init__.py
treep/catkin_make.py
treep/cmake.py
treep/coloring.py
treep/compiler.py
treep/configuration.py
treep/console_manager.py
treep/display_doc.py
treep/exceptions.py
treep/files.py
treep/interactive.py
treep/list_git_repos.py
treep/multiprocess.py
treep/pip.py
treep/process_calls.py
treep/project.py
treep/projects.py
treep/read_compilation_file_python2.py
treep/read_compilation_file_python3.py
treep/repository.py
treep/setup_treepcd.sh
treep/ssh.py
treep/status.py
treep/treep_git.py
treep/version.py
treep-1.52.data/scripts/treep
treep-1.52.data/scripts/treep_to_yaml
treep-1.52.dist-info/LICENSE
treep-1.52.dist-info/METADATA
treep-1.52.dist-info/WHEEL
treep-1.52.dist-info/top_level.txt
treep-1.52.dist-info/RECORD
