Metadata-Version: 2.1
Name: treep
Version: 1.52
Summary: managing git projects structured in tree in python
Home-page: https://gitlab.is.tue.mpg.de/amd-clmc/treep
Author: Vincent Berenz
Author-email: vberenz@tuebingen.mpg.de
License: GPLv3
Keywords: project git tree
Platform: UNKNOWN
Classifier: License :: OSI Approved :: GNU General Public License v3 (GPLv3)
Classifier: Programming Language :: Python :: 3
Requires-Dist: argcomplete
Requires-Dist: colorama
Requires-Dist: future
Requires-Dist: gitpython
Requires-Dist: lightargs
Requires-Dist: pyyaml
